django_dsgov-0.3.dist-info/licenses/LICENSE
dsgov/__init__.py
dsgov/apps.py
dsgov/utils.py
dsgov/static/dsgov/dist/css/rawline.css
dsgov/static/dsgov/dist/css/styles.css
dsgov/static/dsgov/dist/css/styles.css.map
dsgov/static/dsgov/dist/css/test.css
dsgov/static/dsgov/dist/font/rawline-100.eot
dsgov/static/dsgov/dist/font/rawline-100.svg
dsgov/static/dsgov/dist/font/rawline-100.ttf
dsgov/static/dsgov/dist/font/rawline-100.woff
dsgov/static/dsgov/dist/font/rawline-100.woff2
dsgov/static/dsgov/dist/font/rawline-100i.eot
dsgov/static/dsgov/dist/font/rawline-100i.svg
dsgov/static/dsgov/dist/font/rawline-100i.ttf
dsgov/static/dsgov/dist/font/rawline-100i.woff
dsgov/static/dsgov/dist/font/rawline-100i.woff2
dsgov/static/dsgov/dist/font/rawline-200.eot
dsgov/static/dsgov/dist/font/rawline-200.svg
dsgov/static/dsgov/dist/font/rawline-200.ttf
dsgov/static/dsgov/dist/font/rawline-200.woff
dsgov/static/dsgov/dist/font/rawline-200.woff2
dsgov/static/dsgov/dist/font/rawline-200i.eot
dsgov/static/dsgov/dist/font/rawline-200i.svg
dsgov/static/dsgov/dist/font/rawline-200i.ttf
dsgov/static/dsgov/dist/font/rawline-200i.woff
dsgov/static/dsgov/dist/font/rawline-200i.woff2
dsgov/static/dsgov/dist/font/rawline-300-.eot
dsgov/static/dsgov/dist/font/rawline-300.eot
dsgov/static/dsgov/dist/font/rawline-300.svg
dsgov/static/dsgov/dist/font/rawline-300.ttf
dsgov/static/dsgov/dist/font/rawline-300.woff
dsgov/static/dsgov/dist/font/rawline-300.woff2
dsgov/static/dsgov/dist/font/rawline-300i.eot
dsgov/static/dsgov/dist/font/rawline-300i.svg
dsgov/static/dsgov/dist/font/rawline-300i.ttf
dsgov/static/dsgov/dist/font/rawline-300i.woff
dsgov/static/dsgov/dist/font/rawline-300i.woff2
dsgov/static/dsgov/dist/font/rawline-400.eot
dsgov/static/dsgov/dist/font/rawline-400.svg
dsgov/static/dsgov/dist/font/rawline-400.ttf
dsgov/static/dsgov/dist/font/rawline-400.woff
dsgov/static/dsgov/dist/font/rawline-400.woff2
dsgov/static/dsgov/dist/font/rawline-400i.eot
dsgov/static/dsgov/dist/font/rawline-400i.svg
django_dsgov-0.3.dist-info/METADATA
django_dsgov-0.3.dist-info/WHEEL
django_dsgov-0.3.dist-info/top_level.txt
django_dsgov-0.3.dist-info/RECORD
