Metadata-Version: 2.4
Name: django-dsgov
Version: 0.3
Summary: Um App Django app para dispobilizar o Design System gov.br para projeto django.
Author-email: Lucas Gueiros <lucas.dgueiros@ufrpe.br>, Eduardo Silva <eduardo.fsilva3@ufrpe.br>
License-Expression: MIT AND (Apache-2.0 OR BSD-2-Clause)
Project-URL: Homepage, https://gitlab.ufrpe.br/websites-ufrpe/django-dsgov/-/wikis/home
Classifier: Environment :: Web Environment
Classifier: Framework :: Django
Classifier: Framework :: Django :: 5.2
Classifier: Intended Audience :: Developers
Classifier: Operating System :: OS Independent
Classifier: Programming Language :: Python
Classifier: Programming Language :: Python :: 3
Classifier: Programming Language :: Python :: 3 :: Only
Classifier: Programming Language :: Python :: 3.10
Classifier: Programming Language :: Python :: 3.11
Classifier: Programming Language :: Python :: 3.12
Classifier: Programming Language :: Python :: 3.13
Classifier: Topic :: Internet :: WWW/HTTP
Classifier: Topic :: Internet :: WWW/HTTP :: Dynamic Content
Requires-Python: >=3.10
License-File: LICENSE
Requires-Dist: django==5.2.3
Dynamic: license-file
